fraug-0.0.1.dist-info/METADATA
fraug-0.0.1.dist-info/WHEEL
fraug-0.0.1.dist-info/license_files/LICENSE
fraug/__init__.py
fraug/fraug.cpython-310-powerpc64le-linux-gnu.so
fraug-0.0.1.dist-info/RECORD
