Metadata-Version: 2.1
Name: fraug
Version: 0.0.1
Classifier: Programming Language :: Rust
Classifier: Programming Language :: Python :: Implementation :: CPython
Classifier: Programming Language :: Python :: Implementation :: PyPy
License-File: LICENSE
Summary: FRAUG (For Realistic AUGmentations) 🐸 library
Home-Page: https://github.com/fraugs/fraug
Author: Loïck Bourdois <loick.bourdois@outlook.com>, Thomas Chaigneau <t.chaigneau.tc@gmail.com>
Author-email: Loïck Bourdois <loick.bourdois@outlook.com>, Thomas Chaigneau <t.chaigneau.tc@gmail.com>
License: Apache-2.0
Requires-Python: >=3.7
Project-URL: Source Code, https://github.com/fraugs/fraug
